locust_plugins/__init__.py
locust_plugins/appinsights_listener.py
locust_plugins/csvreader.py
locust_plugins/debug.py
locust_plugins/embedded_resource_manager.py
locust_plugins/jmeter_listener.py
locust_plugins/kafka.py
locust_plugins/listeners.py
locust_plugins/mongoreader.py
locust_plugins/transaction_manager.py
locust_plugins/users.py
locust_plugins/utils.py
locust_plugins/wait_time.py
thickly_plugins-1.0.19.dist-info/LICENSE
thickly_plugins-1.0.19.dist-info/METADATA
thickly_plugins-1.0.19.dist-info/WHEEL
thickly_plugins-1.0.19.dist-info/top_level.txt
thickly_plugins-1.0.19.dist-info/RECORD
